xontrib/expand_braces.py
xontrib_brace_expansion-0.1.0.dist-info/LICENSE
xontrib_brace_expansion-0.1.0.dist-info/METADATA
xontrib_brace_expansion-0.1.0.dist-info/WHEEL
xontrib_brace_expansion-0.1.0.dist-info/RECORD
